pyproject.toml
setup.cfg
setup.py
src/crosslab/soa_services/electrical/__init__.py
src/crosslab/soa_services/electrical/electrical_connection_service.py
src/crosslab/soa_services/electrical/messages.py
src/crosslab/soa_services/electrical/py.typed
src/crosslab/soa_services/electrical/signal_interface.py
src/crosslab/soa_services/electrical/signal_interfaces/__init__.py
src/crosslab/soa_services/electrical/signal_interfaces/gpio.py
src/crosslab_soa_service_electrical.egg-info/PKG-INFO
src/crosslab_soa_service_electrical.egg-info/SOURCES.txt
src/crosslab_soa_service_electrical.egg-info/dependency_links.txt
src/crosslab_soa_service_electrical.egg-info/requires.txt
src/crosslab_soa_service_electrical.egg-info/top_level.txt
tests/test_gpio.py
tests/test_standard.py